[
     {
          "x": 10,
          "y": 10,
          "w": 250,
          "h": 200
     },
     {
          "x": 270,
          "y": 10,
          "w": 250,
          "h": 200
     },
     {
          "x": 530,
          "y": 10,
          "w": 250,
          "h": 200
     },
     {
          "x": 10,
          "y": 220,
          "w": 250,
          "h": 200
     },
     {
          "x": 270,
          "y": 220,
          "w": 250,
          "h": 200
     },
     {
          "x": 530,
          "y": 220,
          "w": 250,
          "h": 200
     }
]